sphinx_catalystcloud_theme/__init__.py
sphinx_catalystcloud_theme/breadcrumbs.html
sphinx_catalystcloud_theme/globaltoc.html
sphinx_catalystcloud_theme/layout.html
sphinx_catalystcloud_theme/localtoc.html
sphinx_catalystcloud_theme/navbar.html
sphinx_catalystcloud_theme/navbarsearchbox.html
sphinx_catalystcloud_theme/navbartoc.html
sphinx_catalystcloud_theme/search.html
sphinx_catalystcloud_theme/searchresults.html
sphinx_catalystcloud_theme/sourcelink.html
sphinx_catalystcloud_theme/theme.conf
sphinx_catalystcloud_theme/static/basic.css
sphinx_catalystcloud_theme/static/bootstrap-sphinx.js
sphinx_catalystcloud_theme/static/cloud-logo.png
sphinx_catalystcloud_theme/static/bootstrap/css/bootstrap-theme.css
sphinx_catalystcloud_theme/static/bootstrap/css/bootstrap-theme.css.map
sphinx_catalystcloud_theme/static/bootstrap/css/bootstrap-theme.min.css
sphinx_catalystcloud_theme/static/bootstrap/css/bootstrap-theme.min.css.map
sphinx_catalystcloud_theme/static/bootstrap/css/bootstrap.css
sphinx_catalystcloud_theme/static/bootstrap/css/bootstrap.css.map
sphinx_catalystcloud_theme/static/bootstrap/css/bootstrap.min.css
sphinx_catalystcloud_theme/static/bootstrap/css/bootstrap.min.css.map
sphinx_catalystcloud_theme/static/bootstrap/fonts/glyphicons-halflings-regular.eot
sphinx_catalystcloud_theme/static/bootstrap/fonts/glyphicons-halflings-regular.svg
sphinx_catalystcloud_theme/static/bootstrap/fonts/glyphicons-halflings-regular.ttf
sphinx_catalystcloud_theme/static/bootstrap/fonts/glyphicons-halflings-regular.woff
sphinx_catalystcloud_theme/static/bootstrap/fonts/glyphicons-halflings-regular.woff2
sphinx_catalystcloud_theme/static/bootstrap/js/bootstrap.js
sphinx_catalystcloud_theme/static/bootstrap/js/bootstrap.min.js
sphinx_catalystcloud_theme/static/bootstrap/js/npm.js
sphinx_catalystcloud_theme/static/cloudtheme/config.codekit
sphinx_catalystcloud_theme/static/cloudtheme/config.rb
sphinx_catalystcloud_theme-0.0.1.dist-info/DESCRIPTION.rst
sphinx_catalystcloud_theme-0.0.1.dist-info/METADATA
sphinx_catalystcloud_theme-0.0.1.dist-info/RECORD
sphinx_catalystcloud_theme-0.0.1.dist-info/WHEEL
sphinx_catalystcloud_theme-0.0.1.dist-info/entry_points.txt
sphinx_catalystcloud_theme-0.0.1.dist-info/metadata.json
sphinx_catalystcloud_theme-0.0.1.dist-info/top_level.txt
